dynamixel_helper/__init__.py
dynamixel_helper/byteify.py
dynamixel_helper/constant.py
dynamixel_helper/dxl_helper.py
dynamixel_helper/dxl_motor.py
dynamixel_helper/tables/AX-12W.json
dynamixel_helper/tables/XL-320.json
dynamixel_helper/tables/XL430-W250.json
dynamixel_helper/tables/XM430-W210.json
dynamixel_helper-1.0.2.dist-info/licenses/LICENSE
dynamixel_helper-1.0.2.dist-info/METADATA
dynamixel_helper-1.0.2.dist-info/WHEEL
dynamixel_helper-1.0.2.dist-info/top_level.txt
dynamixel_helper-1.0.2.dist-info/RECORD
