Metadata-Version: 2.4
Name: dynamixel_helper
Version: 1.0.2
Summary: A lightweight, intuitive tool that makes Dynamixel control easier—skip the complexity of the official SDK.
Author-email: Hong-ryul Jung <jung.hr.1206@gmail.com>
License-Expression: MIT
Project-URL: Homepage, https://github.com/ryul1206/dynamixel-helper
Project-URL: Changelog, https://github.com/ryul1206/dynamixel-helper/blob/main/CHANGELOG.md
Keywords: dynamixel
Classifier: Programming Language :: Python :: 3
Classifier: Programming Language :: Python :: 2
Requires-Python: !=3.0.*,!=3.1.*,!=3.2.*,!=3.3.*,<4,>=2.7
License-File: LICENSE
Requires-Dist: dynamixel_sdk>=3
Dynamic: license-file
